rdftools/__init__.py
rdftools/scripts/__init__.py
rdftools/scripts/convert.py
rdftools/scripts/query.py
rdftools/scripts/rdf.py
rdftools/scripts/select.py
rdftools/scripts/shell.py
rdftools/scripts/validate.py
rdftools-0.1.0.dist-info/DESCRIPTION.rst
rdftools-0.1.0.dist-info/METADATA
rdftools-0.1.0.dist-info/RECORD
rdftools-0.1.0.dist-info/WHEEL
rdftools-0.1.0.dist-info/entry_points.txt
rdftools-0.1.0.dist-info/metadata.json
rdftools-0.1.0.dist-info/top_level.txt
test/__init__.py
test/test_shell_commands.py
