Metadata-Version: 2.0
Name: rdftools
Version: 0.1.0
Summary: Command-line tools for RDF
Home-page: https://github.com/johnstonskj/rdftools
Author: Simon Johnston
Author-email: johnstonskj@gmail.com
License: UNKNOWN
Keywords: development,RDF
Platform: UNKNOWN
Classifier: Development Status :: 3 - Alpha
Classifier: Intended Audience :: Developers
Classifier: Topic :: Software Development :: Build Tools
Classifier: License :: OSI Approved :: MIT License
Classifier: Programming Language :: Python :: 3
Classifier: Programming Language :: Python :: 3.4
Classifier: Programming Language :: Python :: 3.5
Classifier: Programming Language :: Python :: 3.6
Requires-Python: >=3.3
Requires-Dist: rdflib (>=4.2)
